{
    "go_mod_package": "github.com/cage1016/ak-script-example",
    "workflow": {
        "folder": ".workflow",
        "name": "AK script example",
        "description": "",
        "category_comment": "category: Tools, Internet, Productivity, Uncategorised",
        "category": "",
        "bundle_id": "com.kaichu.akscriptexample",
        "created_by": "",
        "web_address": "https://github.com/cage1016/ak-script-example",
        "version": "0.1.0"
    },
    "update": {
        "github_repo": "https://github.com/cage1016/ak-script-example"
    },
    "license": {
        "type_comment": "support license https://github.com/nishanths/license",
        "type": "mit",
        "year": "2023",
        "name": "KAI CHU CHUNG"
    },
    "gon": {
        "application_identity": ""
    }
}